pyqgraf/LICENSE
pyqgraf/__init__.py
pyqgraf/model.py
pyqgraf/qgraf.py
pyqgraf/wrap.py
pyqgraf-0.0.19.dist-info/METADATA
pyqgraf-0.0.19.dist-info/WHEEL
pyqgraf-0.0.19.dist-info/RECORD
