Metadata-Version: 2.4
Name: pyqgraf
Version: 0.0.19
Summary: PyQgraf is a Python wrapper for Qgraf, a Feynman diagram generator.
Project-URL: Documentation, https://github.com/APN-Pucky/pyqgraf#readme
Project-URL: Issues, https://github.com/APN-Pucky/pyqgraf/issues
Project-URL: Source, https://github.com/APN-Pucky/pyqgraf/
Author-email: Alexander Puck Neuwirth <alexander@neuwirth-informatik.de>
Classifier: Development Status :: 4 - Beta
Classifier: Intended Audience :: Developers
Classifier: Intended Audience :: Science/Research
Classifier: License :: OSI Approved :: BSD License
Classifier: Programming Language :: Python
Classifier: Programming Language :: Python :: 3.8
Classifier: Programming Language :: Python :: 3.9
Classifier: Programming Language :: Python :: 3.10
Classifier: Programming Language :: Python :: 3.11
Classifier: Programming Language :: Python :: 3.12
Classifier: Programming Language :: Python :: 3.13
Classifier: Programming Language :: Python :: Implementation :: CPython
Classifier: Programming Language :: Python :: Implementation :: PyPy
Classifier: Topic :: Scientific/Engineering
Requires-Python: >=3.8
Requires-Dist: requests
Requires-Dist: scikit-build
Requires-Dist: smpl-io
Provides-Extra: dev
Requires-Dist: pre-commit; extra == 'dev'
Provides-Extra: test
Requires-Dist: pytest; extra == 'test'
Requires-Dist: pytest-cov; extra == 'test'
